{
  "formatVersion": 1,
  "database": {
    "version": 2,
    "identityHash": "8636d5d61df7f82a533a59bf0a5dd93b",
    "entities": [
      {
        "tableName": "rooms",
        "createSql": "CREATE TABLE IF NOT EXISTS `${TABLE_NAME}` (`key` TEXT NOT NULL, `state` INTEGER NOT NULL, `timestamp` INTEGER NOT NULL, `dots` TEXT, `type` INTEGER NOT NULL, `is_send` INTEGER NOT NULL, `user_1_id` TEXT, `user_1_name` TEXT, `user_2_id` TEXT, `user_2_name` TEXT, PRIMARY KEY(`key`))",
        "fields": [
          {
            "fieldPath": "key",
            "columnName": "key",
            "affinity": "TEXT",
            "notNull": true
          },
          {
            "fieldPath": "state",
            "columnName": "state",
            "affinity": "INTEGER",
            "notNull": true
          },
          {
            "fieldPath": "timestamp",
            "columnName": "timestamp",
            "affinity": "INTEGER",
            "notNull": true
          },
          {
            "fieldPath": "dots",
            "columnName": "dots",
            "affinity": "TEXT",
            "notNull": false
          },
          {
            "fieldPath": "type",
            "columnName": "type",
            "affinity": "INTEGER",
            "notNull": true
          },
          {
            "fieldPath": "isSend",
            "columnName": "is_send",
            "affinity": "INTEGER",
            "notNull": true
          },
          {
            "fieldPath": "user1.id",
            "columnName": "user_1_id",
            "affinity": "TEXT",
            "notNull": false
          },
          {
            "fieldPath": "user1.name",
            "columnName": "user_1_name",
            "affinity": "TEXT",
            "notNull": false
          },
          {
            "fieldPath": "user2.id",
            "columnName": "user_2_id",
            "affinity": "TEXT",
            "notNull": false
          },
          {
            "fieldPath": "user2.name",
            "columnName": "user_2_name",
            "affinity": "TEXT",
            "notNull": false
          }
        ],
        "primaryKey": {
          "columnNames": [
            "key"
          ],
          "autoGenerate": false
        },
        "indices": [],
        "foreignKeys": []
      }
    ],
    "setupQueries": [
      "CREATE TABLE IF NOT EXISTS room_master_table (id INTEGER PRIMARY KEY,identity_hash TEXT)",
      "INSERT OR REPLACE INTO room_master_table (id,identity_hash) VALUES(42, \"8636d5d61df7f82a533a59bf0a5dd93b\")"
    ]
  }
}